flask_consent/__init__.py
flask_consent/injection.html
flask_consent/version.py
Flask_Consent-0.0.3.dist-info/LICENSE
Flask_Consent-0.0.3.dist-info/METADATA
Flask_Consent-0.0.3.dist-info/WHEEL
Flask_Consent-0.0.3.dist-info/top_level.txt
Flask_Consent-0.0.3.dist-info/zip-safe
Flask_Consent-0.0.3.dist-info/RECORD
