Metadata-Version: 2.1
Name: Flask-Consent
Version: 0.0.3
Summary: Handle user (cookie) consent in Flask projects
Home-page: https://github.com/02JanDal/Flask-Consent
Author: Jan Dalheimer
Author-email: jan@dalheimer.de
License: MIT
Platform: UNKNOWN
Classifier: Development Status :: 3 - Alpha
Classifier: Environment :: Web Environment
Classifier: Framework :: Flask
Classifier: Intended Audience :: Developers
Classifier: License :: OSI Approved :: MIT License
Classifier: Programming Language :: Python :: 3.7
Classifier: Programming Language :: Python :: 3.8
Classifier: Programming Language :: Python :: 3.9
Classifier: Topic :: Internet :: WWW/HTTP
Requires-Python: ~=3.7
Requires-Dist: Flask (>=1.0.0)
